dotcfg/__init__.py
dotcfg/collections.py
dotcfg/configuration.py
dotcfg/engine.py
dotcfg/errors.py
dotcfg/py.typed
dotcfg/types.py
dotcfg/utils.py
dotcfg-0.1.6.dist-info/LICENSE.rst
dotcfg-0.1.6.dist-info/WHEEL
dotcfg-0.1.6.dist-info/METADATA
dotcfg-0.1.6.dist-info/RECORD
