Metadata-Version: 2.1
Name: dotcfg
Version: 0.1.6
Summary: 
Author: Alex Cano
Author-email: alexjcano1994@gmail.com
Requires-Python: >=3.7,<4.0
Classifier: Programming Language :: Python :: 3
Classifier: Programming Language :: Python :: 3.10
Classifier: Programming Language :: Python :: 3.7
Classifier: Programming Language :: Python :: 3.8
Classifier: Programming Language :: Python :: 3.9
Requires-Dist: python-box (>=5.2.0,<6.0.0)
Requires-Dist: toml (>=0.10.2,<0.11.0)
